{"name":"Enter data to register","id":"pagedemo;enter-data-to-register","testSteps":[{"number":1,"description":"Given tania wants to register in demo automation testing","duration":6,"startTime":"2022-04-26T13:44:30.380-05:00[America/Bogota]","result":"PENDING","precondition":false,"level":0,"lineNumber":0},{"number":2,"description":"When she enters the data in the form","duration":3,"startTime":"2022-04-26T13:44:30.389-05:00[America/Bogota]","result":"IGNORED","precondition":false,"level":0,"lineNumber":0},{"number":3,"description":"Then she loads the information in the submit button","duration":7,"startTime":"2022-04-26T13:44:30.393-05:00[America/Bogota]","result":"IGNORED","precondition":false,"level":0,"lineNumber":0}],"userStory":{"id":"pagedemo","storyName":"pageDemo","path":"src/test/resources/features/pageDemo.feature","narrative":"    As a user I want to fill in data on the page demo automation testing to register and verify a component","type":"feature"},"featureTag":{"name":"Features/pageDemo","type":"feature","displayName":"Features/pageDemo"},"title":"Enter data to register","tags":[{"name":"scenario1","type":"tag","displayName":"scenario1"},{"name":"pageDemo","type":"feature","displayName":"pageDemo"},{"name":"stories","type":"tag","displayName":"stories"}],"startTime":"2022-04-26T13:44:30.308-05:00[America/Bogota]","duration":94,"projectKey":"","annotatedResult":"PENDING","isManualTestingUpToDate":false,"manual":false,"testSource":"Cucumber","result":"PENDING"}